wang_editor/__init__.py
wang_editor/admin.py
wang_editor/apps.py
wang_editor/fields.py
wang_editor/models.py
wang_editor/tests.py
wang_editor/urls.py
wang_editor/views.py
wang_editor/widgets.py
wang_editor/migrations/__init__.py
django_wang_echo_editor-0.1.3.dist-info/METADATA
django_wang_echo_editor-0.1.3.dist-info/WHEEL
django_wang_echo_editor-0.1.3.dist-info/top_level.txt
django_wang_echo_editor-0.1.3.dist-info/RECORD
