Metadata-Version: 2.1
Name: django-wang-echo-editor
Version: 0.1.3
Summary: Django Admin 中使用 wangEditor 富文本编辑器
Home-page: 
Author: Echo Chu
Author-email: 395150457@qq.com
License: MIT License
Classifier: Environment :: Web Environment
Classifier: Framework :: Django
Classifier: Framework :: Django :: 4.2
Classifier: Intended Audience :: Developers
Classifier: License :: OSI Approved :: MIT License
Classifier: Operating System :: OS Independent
Classifier: Programming Language :: Python :: 3.10
Classifier: Topic :: Internet :: WWW/HTTP
Classifier: Topic :: Internet :: WWW/HTTP :: Dynamic Content
Requires-Dist: django-js-asset
